mocap2d/2dmocap-edit.py
mocap2d/__init__.py
mocap2d/detect.py
mocap2d/editor.py
mocap2d/mocap2d.py
unity_2dmocap-0.1.2.dist-info/LICENSE
unity_2dmocap-0.1.2.dist-info/METADATA
unity_2dmocap-0.1.2.dist-info/WHEEL
unity_2dmocap-0.1.2.dist-info/entry_points.txt
unity_2dmocap-0.1.2.dist-info/top_level.txt
unity_2dmocap-0.1.2.dist-info/RECORD
