Metadata-Version: 2.1
Name: unity-2dmocap
Version: 0.1.2
Summary: Python application for Unity Asset of 2D motion capture
Home-page: http://www.github.com/k2sebeom/unity-2dmocap
Author: SeBeom Lee
Author-email: slee5@oberlin.edu
License: MIT
Project-URL: Maintainer, https://github.com/k2sebeom
Project-URL: Source, https://github.com/unity-2dmocap
Project-URL: Tracker, https://github.com/k2sebeom/unity-2dmocap/issues
Keywords: python,motion capture,unity
Platform: UNKNOWN
Classifier: Programming Language :: Python
Classifier: Programming Language :: Python :: 3.6
Classifier: Programming Language :: Python :: 3.7
Classifier: License :: OSI Approved :: MIT License
Requires-Dist: torch
Requires-Dist: torchvision
Requires-Dist: opencv-python
Requires-Dist: numpy
